.clang-format
.flake8
.gitignore
.gitmodules
CHANGELOG.md
CODEOWNERS
CODE_OF_CONDUCT
Dockerfile
Dockerfile-cuda
Dockerfile-embedded
LICENSE
MANIFEST.in
Makefile
README.md
__init__.py
description.txt
packages.txt
setup.py
./src/opendr/__init__.py
./src/opendr/_setup.py
./src/opendr/_version.py
./src/opendr/control/__init__.py
./src/opendr/engine/__init__.py
./src/opendr/engine/constants.py
./src/opendr/engine/data.py
./src/opendr/engine/datasets.py
./src/opendr/engine/example_learner.py
./src/opendr/engine/learners.py
./src/opendr/engine/target.py
./src/opendr/perception/__init__.py
./src/opendr/perception/speech_transcription/__init__.py
./src/opendr/perception/speech_transcription/vosk/README.md
./src/opendr/perception/speech_transcription/vosk/__init__.py
./src/opendr/perception/speech_transcription/vosk/dependencies.ini
./src/opendr/perception/speech_transcription/vosk/vosk_learner.py
./src/opendr/perception/speech_transcription/whisper/README.md
./src/opendr/perception/speech_transcription/whisper/__init__.py
./src/opendr/perception/speech_transcription/whisper/dependencies.ini
./src/opendr/perception/speech_transcription/whisper/whisper_learner.py
./src/opendr/planning/__init__.py
./src/opendr/simulation/__init__.py
./src/opendr/utils/__init__.py
./src/opendr_toolkit_speech_transcription.egg-info/PKG-INFO
./src/opendr_toolkit_speech_transcription.egg-info/SOURCES.txt
./src/opendr_toolkit_speech_transcription.egg-info/dependency_links.txt
./src/opendr_toolkit_speech_transcription.egg-info/requires.txt
./src/opendr_toolkit_speech_transcription.egg-info/top_level.txt
src/opendr/_setup.py
src/opendr/_version.py
src/opendr/perception/speech_transcription/__init__.py
src/opendr/perception/speech_transcription/vosk/README.md
src/opendr/perception/speech_transcription/vosk/__init__.py
src/opendr/perception/speech_transcription/vosk/dependencies.ini
src/opendr/perception/speech_transcription/vosk/vosk_learner.py
src/opendr/perception/speech_transcription/whisper/README.md
src/opendr/perception/speech_transcription/whisper/__init__.py
src/opendr/perception/speech_transcription/whisper/dependencies.ini
src/opendr/perception/speech_transcription/whisper/whisper_learner.py