Metadata-Version: 1.0
Name: opendr-toolkit-speech-transcription
Version: 3.0.0
Summary: Open Deep Learning Toolkit for Robotics (submodule: perception/speech_transcription)
Home-page: https://github.com/opendr-eu/opendr
Author: OpenDR consortium
Author-email: tefas@csd.auth.gr
License: LICENSE
Platform: UNKNOWN
